dnsdb/__init__.py
dnsdb/cli/cli.py
dnsdb/cli/utils.py
dnsdb/dnsdb.py
dnsdb/utils.py
dnsdb-0.2.5.dist-info/entry_points.txt
dnsdb-0.2.5.dist-info/LICENSE
dnsdb-0.2.5.dist-info/WHEEL
dnsdb-0.2.5.dist-info/METADATA
dnsdb-0.2.5.dist-info/RECORD
