Metadata-Version: 2.1
Name: dnsdb
Version: 0.2.5
Summary: Python client for Farsight Security's DNSDB API
Home-page: https://github.com/giovino/fsi-dnsdb
License: MIT
Keywords: security
Author: Gabriel Iovino
Author-email: giovino@gmail.com
Requires-Python: >=3.6,<4.0
Classifier: License :: OSI Approved :: MIT License
Classifier: Programming Language :: Python :: 3
Classifier: Programming Language :: Python :: 3.6
Classifier: Programming Language :: Python :: 3.7
Requires-Dist: diskcache (>=3.1,<4.0)
Requires-Dist: python-dateutil (>=2.8,<3.0)
Requires-Dist: requests (>=2.21,<3.0)
Project-URL: Repository, https://github.com/giovino/fsi-dnsdb
